imjoy_elfinder/VERSION
imjoy_elfinder/__init__.py
imjoy_elfinder/__main__.py
imjoy_elfinder/api_const.py
imjoy_elfinder/app.py
imjoy_elfinder/elfinder.py
imjoy_elfinder/settings.py
imjoy_elfinder/util.py
imjoy_elfinder/views.py
imjoy_elfinder/templates/elfinder/elfinder.html
imjoy_elfinder/templates/elfinder/filebrowser.jinja2
imjoy_elfinder/templates/elfinder/main.css
imjoy_elfinder/templates/elfinder/main.js
tests/__init__.py
tests/conftest.py
tests/test_elfinder.py
tests/test_sample.py
tests/test_views.py
imjoy_elfinder-0.1.63.dist-info/LICENSE
imjoy_elfinder-0.1.63.dist-info/METADATA
imjoy_elfinder-0.1.63.dist-info/WHEEL
imjoy_elfinder-0.1.63.dist-info/entry_points.txt
imjoy_elfinder-0.1.63.dist-info/top_level.txt
imjoy_elfinder-0.1.63.dist-info/RECORD
