Metadata-Version: 2.1
Name: imjoy-elfinder
Version: 0.1.63
Summary: An elfinder connector built with FastAPI, specifically for working with jupyter server proxy.
Home-page: https://github.com/imjoy-team/imjoy-elfinder
Author: ImJoy-Team
License: MIT
Classifier: Development Status :: 5 - Production/Stable
Classifier: Environment :: Web Environment
Classifier: Intended Audience :: Developers
Classifier: License :: OSI Approved :: MIT License
Classifier: Operating System :: OS Independent
Classifier: Programming Language :: Python
Classifier: Programming Language :: Python :: 3.7
Classifier: Programming Language :: Python :: 3.8
Classifier: Programming Language :: Python :: 3.9
Classifier: Programming Language :: Python :: 3.10
Classifier: Framework :: FastAPI 
Classifier: Topic :: Internet
Requires-Python: >=3.7
License-File: LICENSE
Requires-Dist: aiofiles
Requires-Dist: elfinder-client
Requires-Dist: fastapi
Requires-Dist: jinja2
Requires-Dist: pathvalidate
Requires-Dist: pillow
Requires-Dist: python-dotenv
Requires-Dist: python-multipart
Requires-Dist: typing-extensions
Requires-Dist: uvicorn[standard]
Requires-Dist: pydantic <2,>=1.8.2
Provides-Extra: jupyter
Requires-Dist: jupyter-server-proxy ; extra == 'jupyter'
